<?xml version="1.0" encoding="UTF-8"?>
<event>
    <name>Collect .xsession-errors</name>
    <name xml:lang="as">.xsession-errors সংগ্ৰহ কৰক</name>
    <name xml:lang="bn_IN">.xsession-errors সংগ্রহ করা হবে</name>
    <name xml:lang="de">.xsession-Fehler einbeziehen</name>
    <name xml:lang="es">Recolectar .xsession-errors</name>
    <name xml:lang="fr">Collecter .xsession-errors</name>
    <name xml:lang="gu">.xsession-errors સંગ્રહો</name>
    <name xml:lang="hi">.xsession-errors जमा करें</name>
    <name xml:lang="it">Acquisizione .xsession-errors</name>
    <name xml:lang="ja">.xsession エラーを収集する</name>
    <name xml:lang="kn">.xsession-errors ಅನ್ನು ಸಂಗ್ರಹಿಸು</name>
    <name xml:lang="ko">.xsession-errors를 수집</name>
    <name xml:lang="ml">.xsession-errors ശേഖരിയ്ക്കുക</name>
    <name xml:lang="mr">.xsession-errors गोळा करा</name>
    <name xml:lang="or">.xsession-errors କୁ ସଂଗ୍ରହ କରନ୍ତୁ</name>
    <name xml:lang="pa"> .xsession-errors ਇਕੱਠੀਆਂ ਕਰੋ</name>
    <name xml:lang="pl">Zbiera plik .xsession-errors</name>
    <name xml:lang="pt">Recolher .xsession-errors</name>
    <name xml:lang="pt_BR">Coletar .xsession-errors</name>
    <name xml:lang="ru">Сбор .xsession-errors</name>
    <name xml:lang="ta">.xsession-பிழைகளைச் சேகரி</name>
    <name xml:lang="te">.xsession-errors సేకరించు</name>
    <name xml:lang="uk">Зібрати дані з .xsession-errors</name>
    <name xml:lang="zh_CN">收集 .xsession-errors</name>
    <name xml:lang="zh_TW">Collect .xsession-errors</name>
    <description>Save relevant lines from ~/.xsession-errors file</description>
    <description xml:lang="as">~/.xsession-errors ফাইলৰ পৰা প্ৰাসংগিক শাৰীসমূহ সংৰক্ষণ কৰক</description>
    <description xml:lang="bn_IN">~/.xsession-errors ফাইলের প্রযোজ্য পংক্তিগুলি সংরক্ষণ করা হবে</description>
    <description xml:lang="de">Relevante Zeilen der Datei ~/.xsession-errors speichern</description>
    <description xml:lang="es">Guarde las líneas importantes del archivo </description>
    <description xml:lang="fi">Tallenna tärkeät rivit tiedostosta ~/.xsession-errors</description>
    <description xml:lang="fr">Enregistre les lignes pertinentes du fichier ~/.xsession-errors</description>
    <description xml:lang="gu">~/.xsession-errors ફાઇલમાંથી સંબંધિત વાક્યોને સંગ્રહો</description>
    <description xml:lang="hi">~/.xsession-errors फ़ाइल से संबंधित पंक्ति सहेजें</description>
    <description xml:lang="it">Salva le righe rilevanti del file </description>
    <description xml:lang="ja">~/.xsession-errors ファイルから関連した行を保存する</description>
    <description xml:lang="kn">~/.xsession-errors file ಇಂದ ಸೂಕ್ತವಾದ ಸಾಲುಗಳನ್ನು ಉಳಿಸು</description>
    <description xml:lang="ko">~/.xsession-errors 파일에서 해당 행을 저장합니다 </description>
    <description xml:lang="ml">~/.xsession-errors ഫയലില്‍ നിന്നും ഉചിതമായ വരികള്‍ സൂക്ഷിയ്ക്കുക</description>
    <description xml:lang="mr">~/.xsession-errors फाइलपासून संबंधित ओळी साठवा</description>
    <description xml:lang="or">~/.xsession-errors ଫାଇଲରୁ ସମ୍ପୃକ୍ତ ଧାଡ଼ିଗୁଡ଼ିକୁ ସଂରକ୍ଷଣ କରନ୍ତୁ</description>
    <description xml:lang="pa">~/.xsession-errors ਫਾਈਲ ਤੋਂ ਮਤਲਬ ਦੀਆਂ ਲਾਈਨਾਂ ਸੰਭਾਲਦਾ ਹੈ</description>
    <description xml:lang="pl">Zapisuje ważne wiersze z pliku ~/.xsession-errors</description>
    <description xml:lang="pt">Guardar linhas relevantes do ficheiro ~/.xsession-errors</description>
    <description xml:lang="pt_BR">Salva linhas relevantes do arquivo ~/.xsession-errors</description>
    <description xml:lang="ru">Извлечение значимых строк из файла ~/.xsession-errors</description>
    <description xml:lang="ta">~/.xsession-errors கோப்பிலிருந்து தொடர்புடைய வரிகளை சேமிக்கிறது</description>
    <description xml:lang="te">~/.xsession-errors ఫైలునుండి సంభందిత లైన్లను దాయి</description>
    <description xml:lang="uk">Зберегти відповідні рядки з файла ~/.xsession-errors</description>
    <description xml:lang="zh_CN">从 ~/.xsession-errors 文件保存相关行</description>
    <description xml:lang="zh_TW">儲存來自於 ~/.xsession-errors 檔案的相關行列</description>
    <long-description>Scans through ~/.xsession-errors file and saves those lines which contain executable's name. The result is saved as 'xsession_errors' element.</long-description>
    <long-description xml:lang="as">~/.xsession-errors ফাইল স্কেন কৰে আৰু সেই শাৰীসমূহ যি এক্সিকিউটেবুলসমূহৰ নাম অন্তৰ্ভুক্ত কৰে সেয়া সংৰক্ষণ কৰে। ফলাফল  'xsession_errors'  উপাদান হিচাপে সংৰক্ষণ কৰা হয়।</long-description>
    <long-description xml:lang="bn_IN">~/.xsession-errors ফাইলের মধ্যে অনুসন্ধান করে ও এক্সেকিউটেবলের নাম সহ পংক্তিগুলিকে সংরক্ষণ করে। 'xsession_errors' এলিমেন্টের মধ্যে ফলাফল সংরক্ষণ করা হয়।</long-description>
    <long-description xml:lang="de">Liest die Datei ~/.xsession-errors ein und speichert die Zeilen, die Namen ausführbarer Dateien enthalten. Das Ergebnis wird als »xsession_errors«-Element gespeichert.</long-description>
    <long-description xml:lang="es">Escanea a través del archivo ~/.xsession-errors y guarda las líneas que contienen el nombre del ejecutable. El resultado se guarda como elemento de  'xsession_errors'.</long-description>
    <long-description xml:lang="fi">Tutkii tiedoston ~/.xsession-errors ja tallentaa rivit, jotka sisältävät suoritettavan tiedoston nimen. Tulos tallennetaan ”xsession_errors”-elementtinä.</long-description>
    <long-description xml:lang="fr">Scanne le fichier ~/.xsession-errors et enregistre les lignes contenant un nom exécutable. Le résultat est enregistré en tant qu'élément 'xsession_errors'.</long-description>
    <long-description xml:lang="gu">~/.xsession-errors ફાઇલ મારફતે સ્કેન થાય છે અને પેલાં વાક્યોનો સંગ્રહ થાય છે કે જે એક્ઝેક્યુટેબલનાં નામને સમાવે છે. પરિણામ 'xsession_errors' ઘટક તરીકે સંગ્રહ થયેલ છે.</long-description>
    <long-description xml:lang="hi">~/.xsession-errors फ़ाइल से स्कैन करें और उन पंक्तियों को सहेजें जो निष्पादनीय नाम समाहित किए है. परिणाम को बतौर 'xsession_errors' तत्व सहेजा गया है.</long-description>
    <long-description xml:lang="it">Esegue la scansione del file ~/.xsession-errors e salva le righe che contengono il nome dell'eseguibile. Il risultato sarà salvato come elemento di 'xsession_errors'.</long-description>
    <long-description xml:lang="ja">~/.xsession-errors ファイルをスキャンして実行ファイル名を含んだ行を保存する。その結果は 'xsession_errors' 要素として保存する</long-description>
    <long-description xml:lang="kn">~/.xsession-errors ಕಡತದ ಮೂಲಕ ಶೋಧಿಸುತ್ತದೆ ಹಾಗು ಕಾರ್ಯಗತಗೊಳಿಸಲಬಲ್ಲ ಹೆಸರನ್ನು ಹೊಂದಿರುವ ಸಾಲುಗಳನ್ನು ಉಳಿಸುತ್ತದೆ. ಫಲಿತಾಂಶವನ್ನು  'xsession_errors' ಘಟಕವಾಗಿ ಉಳಿಸಲಾಗುತ್ತದೆ.</long-description>
    <long-description xml:lang="ko">~/.xsession-errors 파일을 스캔하여 실행 가능한 이름이 있는 행을 저장합니다. 결과는 'xsession_errors' 요소로서 저장됩니다. </long-description>
    <long-description xml:lang="ml">~/.xsession-errors ഫയല്‍ പരിശോധിച്ചു്, പ്രവര്‍ത്തിയ്ക്കുന്നവയുടെ പേരടങ്ങുന്ന വരികള്‍ സൂക്ഷിയ്ക്കുന്നു. ഇതിന്റെ ഫലം 'xsession_errors' എലമെന്റായി സൂക്ഷിയ്ക്കുന്നു.</long-description>
    <long-description xml:lang="mr">~/.xsession-errors फाइल स्कॅन करतो व एक्जीक्युटेबल नावे समाविष्टीत असणाऱ्या ओळी साठवतो. परिणाम 'xsession_errors' घटक म्हणून साठवले जातात.</long-description>
    <long-description xml:lang="or">~/.xsession-errors ଫାଇଲ ମାଧ୍ଯମରେ କ୍ରମବୀକ୍ଷଣ କରିଥାଏ ଏବଂ ନିଷ୍ପାଦନ ଯୋଗ୍ୟ ନାମ ଧାରଣ କରିଥିବା ଧାଡ଼ିଗୁଡ଼ିକୁ ସଂରକ୍ଷଣ କରିଥାଏ। ଫଳାଫଳକୁ 'xsession_errors' ଉପାଦାନ ଭାବରେ ସଂରକ୍ଷଣ କରାଯାଇଥାଏ।</long-description>
    <long-description xml:lang="pa">~/.xsession-errors ਫਾਈਲ ਵਿੱਚ ਖੋਜਦਾ ਹੈ ਅਤੇ ਉਹ ਸਤਰਾਂ ਸੰਭਾਲਦਾ ਹੈ ਜਿਨ੍ਹਾਂ ਵਿੱਚ ਐਗਜ਼ੀਕਿਊਟੇਬਲ ਦਾ ਨਾਂ ਹੁੰਦਾ ਹੈ। ਨਤੀਜੇ ਨੂੰ 'xsession_errors' ਤੱਤ ਦੇ ਤੌਰ ਤੇ ਸੰਭਾਲਿਆ ਜਾਂਦਾ ਹੈ।</long-description>
    <long-description xml:lang="pl">Skanuje plik ~/.xsession-errors i zapisuje te wiersze, które zawierają nazwę pliku wykonywalnego. Wynik jest zapisywany jako element "xsession_errors".</long-description>
    <long-description xml:lang="pt_BR">Escaneia o arquivo ~/.xsession-errors e salvas essas linhas que contém nomes executáveis. O resultado é salvo como um elemento 'xsession_errors'.</long-description>
    <long-description xml:lang="ru">Проверяет ~/.xsession-errors и сохраняет строки, содержащие имя исполняемого модуля. Результат сохраняется в «xsession_errors».</long-description>
    <long-description xml:lang="ta">~/.xsession-errors கோப்பு மற்றும் ஸ்கேன் வழியாக அந்த வரிகளை நிறைவேற்றக்கூடிய பெயரை கொண்டுள்ளதை சேமிக்கின்றது. முடிவானது 'xsession_errors' உருப்படியாக சேமிக்கப்பட்டது.</long-description>
    <long-description xml:lang="te">~/.xsession-errors ఫైలు గుండా స్కాన్ చేయును మరియు యెగ్జిక్యూటబుల్ యొక్క పేరు కలిగివుండే వరుసలను దాయును. ఫలితం 'xsession_errors'  మూలకంగా దాయబడును.</long-description>
    <long-description xml:lang="uk">Виконує пошук у файлі ~/.xsession-errors і зберігає ті рядки, які містять назву виконуваного файла. Результат зберігається у елементі «xsession_errors».</long-description>
    <long-description xml:lang="zh_CN">扫描 ~/.xsession-errors 文件并保存包含可执行文件名称的行。结果保存为 'xsession_errors' 元素。</long-description>
    <long-description xml:lang="zh_TW">掃描 ~/.xsession-errors 檔案並儲存那些包含了可執行檔名稱的行列。結果會被儲存為「xsession_errors」項目。</long-description>
    <creates-items>xsession_errors</creates-items>
</event>